build/lib/build/lib/build/lib/build/lib/build/lib/build/lib/build/lib/src/main.py
build/lib/build/lib/build/lib/build/lib/build/lib/build/lib/build/lib/src/player.py
build/lib/build/lib/build/lib/build/lib/build/lib/build/lib/build/lib/src/podcasts.py
build/lib/build/lib/build/lib/build/lib/build/lib/build/lib/build/lib/src/radio_stations.py
build/lib/build/lib/build/lib/build/lib/build/lib/build/lib/build/lib/venv/bin/rst2html.py
build/lib/build/lib/build/lib/build/lib/build/lib/build/lib/build/lib/venv/bin/rst2html4.py
build/lib/build/lib/build/lib/build/lib/build/lib/build/lib/build/lib/venv/bin/rst2html5.py
build/lib/build/lib/build/lib/build/lib/build/lib/build/lib/build/lib/venv/bin/rst2latex.py
build/lib/build/lib/build/lib/build/lib/build/lib/build/lib/build/lib/venv/bin/rst2man.py
build/lib/build/lib/build/lib/build/lib/build/lib/build/lib/build/lib/venv/bin/rst2odt.py
build/lib/build/lib/build/lib/build/lib/build/lib/build/lib/build/lib/venv/bin/rst2odt_prepstyles.py
build/lib/build/lib/build/lib/build/lib/build/lib/build/lib/build/lib/venv/bin/rst2pseudoxml.py
build/lib/build/lib/build/lib/build/lib/build/lib/build/lib/build/lib/venv/bin/rst2s5.py
build/lib/build/lib/build/lib/build/lib/build/lib/build/lib/build/lib/venv/bin/rst2xetex.py
build/lib/build/lib/build/lib/build/lib/build/lib/build/lib/build/lib/venv/bin/rst2xml.py
build/lib/build/lib/build/lib/build/lib/build/lib/build/lib/build/lib/venv/bin/rstpep2html.py
build/lib/build/lib/build/lib/build/lib/build/lib/build/lib/src/main.py
build/lib/build/lib/build/lib/build/lib/build/lib/build/lib/src/player.py
build/lib/build/lib/build/lib/build/lib/build/lib/build/lib/src/podcasts.py
build/lib/build/lib/build/lib/build/lib/build/lib/build/lib/src/radio_stations.py
build/lib/build/lib/build/lib/build/lib/build/lib/build/lib/venv/bin/rst2html.py
build/lib/build/lib/build/lib/build/lib/build/lib/build/lib/venv/bin/rst2html4.py
dev_radio-1.0.10.dist-info/LICENSE
dev_radio-1.0.10.dist-info/METADATA
dev_radio-1.0.10.dist-info/WHEEL
dev_radio-1.0.10.dist-info/entry_points.txt
dev_radio-1.0.10.dist-info/top_level.txt
dev_radio-1.0.10.dist-info/RECORD
