Metadata-Version: 2.1
Name: dev-radio
Version: 1.0.10
Summary: A simple cmdline radio to listen to python podcasts and some music.
Home-page: https://github.com/Legion-God/dev-radio
Author: Shubhendra Rajkarne
Author-email: srajkarne11@gmail.com
License: UNKNOWN
Platform: UNKNOWN
Classifier: Programming Language :: Python :: 3
Classifier: Environment :: Console
Classifier: License :: OSI Approved :: MIT License
Classifier: Operating System :: OS Independent
Classifier: Topic :: Multimedia :: Sound/Audio
Requires-Python: >=3.6
Requires-Dist: requests
Requires-Dist: feedparser
Requires-Dist: click
Requires-Dist: prettytable
Requires-Dist: python-vlc
